{
  "_class": "group",
  "booleanOperation": -1,
  "clippingMaskMode": 0,
  "do_objectID": "C045AEFD-54F4-4245-B3F6-816D31D12CEE",
  "exportOptions": {
    "_class": "exportOptions",
    "do_objectID": "562FFBA8-C424-4969-B1DF-C08E36A9720D",
    "exportFormats": [
    ],
    "includedLayerIds": [
    ],
    "layerOptions": 0,
    "shouldTrim": false
  },
  "frame": {
    "_class": "rect",
    "constrainProportions": false,
    "do_objectID": "67F22EF6-381B-400B-B837-566978142AC4",
    "height": 172,
    "width": 307,
    "x": 54,
    "y": 3375
  },
  "hasClickThrough": false,
  "hasClippingMask": false,
  "isFixedToViewport": false,
  "isFlippedHorizontal": false,
  "isFlippedVertical": false,
  "isLocked": false,
  "isVisible": true,
  "layerListExpandedType": 2,
  "layers": [
    {
      "class": "text",
      "id": "143B8F92-E04C-4F78-B225-171EBB628742"
    },
    {
      "class": "text",
      "id": "80D94EDA-F515-491C-A374-19BE806C26EB"
    },
    {
      "class": "text",
      "id": "433B4048-55E0-4F12-994C-42965360939F"
    },
    {
      "class": "symbolInstance",
      "id": "F07070C1-9B8D-4C51-8928-93009545185E"
    }
  ],
  "name": "Group Copy 9",
  "nameIsFixed": false,
  "resizingConstraint": 63,
  "resizingType": 0,
  "rotation": 0,
  "sharedStyleID": "DB892485-AF39-49C9-BBC2-EFB89DAF4104",
  "shouldBreakMaskChain": false,
  "style": {
    "_class": "style",
    "blur": {
      "_class": "blur",
      "center": "{0.5, 0.5}",
      "do_objectID": "80E50987-8BCB-4D77-8C85-8D937F7076A3",
      "isEnabled": false,
      "motionAngle": 0,
      "radius": 6,
      "saturation": 1,
      "type": 0
    },
    "borders": [
      {
        "_class": "border",
        "color": {
          "_class": "color",
          "alpha": 1,
          "blue": 0.592,
          "green": 0.592,
          "red": 0.592
        },
        "fillType": 0,
        "isEnabled": false,
        "position": 1,
        "thickness": 0.6
      }
    ],
    "do_objectID": "C61CFD79-0106-4E9B-82E9-5378CDDA1638",
    "endMarkerType": 0,
    "fills": [
      {
        "_class": "fill",
        "color": {
          "_class": "color",
          "alpha": 1,
          "blue": 0.2549019607843137,
          "green": 0.2274509803921569,
          "red": 0.2078431372549019
        },
        "fillType": 0,
        "isEnabled": true,
        "noiseIndex": 0,
        "noiseIntensity": 0,
        "patternFillType": 1,
        "patternTileScale": 1
      }
    ],
    "miterLimit": 10,
    "startMarkerType": 0,
    "windingRule": 1
  }
}