{
  "_class": "shapePath",
  "booleanOperation": -1,
  "clippingMaskMode": 0,
  "do_objectID": "55C0D704-D3CE-4A11-935C-D094F0724B01",
  "edited": true,
  "exportOptions": {
    "_class": "exportOptions",
    "do_objectID": "1C03E09A-8AF4-4900-A744-CC93CE4D723F",
    "exportFormats": [
    ],
    "includedLayerIds": [
    ],
    "layerOptions": 0,
    "shouldTrim": false
  },
  "frame": {
    "_class": "rect",
    "constrainProportions": false,
    "do_objectID": "3D6AE9E1-0D30-4B49-8A90-797CED040835",
    "height": 1.322475570032623,
    "width": 1.321428571428612,
    "x": 259.0746044422062,
    "y": 221.9480332247557
  },
  "hasClippingMask": false,
  "isClosed": false,
  "isFixedToViewport": false,
  "isFlippedHorizontal": false,
  "isFlippedVertical": false,
  "isLocked": false,
  "isVisible": true,
  "layerListExpandedType": 0,
  "name": "Fill 399",
  "nameIsFixed": false,
  "pointRadiusBehaviour": 1,
  "points": [
    {
      "_class": "curvePoint",
      "cornerRadius": 0,
      "curveFrom": "{0.48454258427634045, 0.65400000000002478}",
      "curveMode": 4,
      "curveTo": "{0.63154258427633181, 0.73500000000001364}",
      "hasCurveFrom": true,
      "hasCurveTo": false,
      "point": "{0.63154258427633181, 0.73500000000001364}"
    },
    {
      "_class": "curvePoint",
      "cornerRadius": 0,
      "curveFrom": "{0.34254258427634454, 0.47200000000000841}",
      "curveMode": 3,
      "curveTo": "{0.354542584276345, 0.61800000000002342}",
      "hasCurveFrom": true,
      "hasCurveTo": true,
      "point": "{0.3505425842763259, 0.57200000000000273}"
    },
    {
      "_class": "curvePoint",
      "cornerRadius": 0,
      "curveFrom": "{0.50154258427633636, 0.30200000000002092}",
      "curveMode": 4,
      "curveTo": "{0.39954258427633249, 0.36700000000001864}",
      "hasCurveFrom": true,
      "hasCurveTo": true,
      "point": "{0.42954258427633363, 0.26500000000001478}"
    },
    {
      "_class": "curvePoint",
      "cornerRadius": 0,
      "curveFrom": "{0.66854258427633795, 0.45900000000000318}",
      "curveMode": 3,
      "curveTo": "{0.61054258427634522, 0.32200000000000273}",
      "hasCurveFrom": true,
      "hasCurveTo": true,
      "point": "{0.63454258427631771, 0.3790000000000191}"
    },
    {
      "_class": "curvePoint",
      "cornerRadius": 0,
      "curveFrom": "{0.63154258427633181, 0.73500000000001364}",
      "curveMode": 4,
      "curveTo": "{0.63754258427633204, 0.56500000000002615}",
      "hasCurveFrom": false,
      "hasCurveTo": true,
      "point": "{0.63154258427633181, 0.73500000000001364}"
    }
  ],
  "resizingConstraint": 63,
  "resizingType": 0,
  "rotation": 0,
  "shouldBreakMaskChain": false,
  "style": {
    "_class": "style",
    "do_objectID": "79EC0812-6751-452B-B3A0-F17FDBA0D3E7",
    "endMarkerType": 0,
    "fills": [
      {
        "_class": "fill",
        "color": {
          "_class": "color",
          "alpha": 1,
          "blue": 0.4037829637527466,
          "green": 0.7383424639701843,
          "red": 0.8472057580947876
        },
        "fillType": 0,
        "isEnabled": true,
        "noiseIndex": 0,
        "noiseIntensity": 0,
        "patternFillType": 1,
        "patternTileScale": 1
      }
    ],
    "miterLimit": 10,
    "startMarkerType": 0,
    "windingRule": 1
  }
}