{
  "_class": "shapePath",
  "booleanOperation": -1,
  "clippingMaskMode": 0,
  "do_objectID": "AE3BFCBC-2753-48DE-8C53-092CD0F6118C",
  "edited": true,
  "exportOptions": {
    "_class": "exportOptions",
    "do_objectID": "BDB57BEF-D366-44E6-AB40-B8216809B9F1",
    "exportFormats": [
    ],
    "includedLayerIds": [
    ],
    "layerOptions": 0,
    "shouldTrim": false
  },
  "frame": {
    "_class": "rect",
    "constrainProportions": false,
    "do_objectID": "3E23A300-66F4-4F0F-A7E3-8C5AE7AE7696",
    "height": 1.322475570032594,
    "width": 1.321428571428726,
    "x": 367.2694151171905,
    "y": 142.5710069226673
  },
  "hasClippingMask": false,
  "isClosed": false,
  "isFixedToViewport": false,
  "isFlippedHorizontal": false,
  "isFlippedVertical": false,
  "isLocked": false,
  "isVisible": true,
  "layerListExpandedType": 0,
  "name": "Fill 1783",
  "nameIsFixed": false,
  "pointRadiusBehaviour": 1,
  "points": [
    {
      "_class": "curvePoint",
      "cornerRadius": 0,
      "curveFrom": "{0.82818855996390539, 0.69304451906683084}",
      "curveMode": 4,
      "curveTo": "{0.91418855996391812, 0.61704451906683744}",
      "hasCurveFrom": true,
      "hasCurveTo": false,
      "point": "{0.91418855996391812, 0.61704451906683744}"
    },
    {
      "_class": "curvePoint",
      "cornerRadius": 0,
      "curveFrom": "{0.55218855996389493, 0.83104451906683607}",
      "curveMode": 4,
      "curveTo": "{0.75018855996393086, 0.76204451906684767}",
      "hasCurveFrom": true,
      "hasCurveTo": true,
      "point": "{0.65718855996391312, 0.8440445190668413}"
    },
    {
      "_class": "curvePoint",
      "cornerRadius": 0,
      "curveFrom": "{0.24418855996390221, 0.76304451906682402}",
      "curveMode": 4,
      "curveTo": "{0.43218855996389038, 0.81704451906682607}",
      "hasCurveFrom": true,
      "hasCurveTo": true,
      "point": "{0.27518855996390812, 0.79804451906684903}"
    },
    {
      "_class": "curvePoint",
      "cornerRadius": 0,
      "curveFrom": "{0.041188559963927673, 0.50804451906682857}",
      "curveMode": 3,
      "curveTo": "{0.18118855996391403, 0.70304451906685017}",
      "hasCurveFrom": true,
      "hasCurveTo": true,
      "point": "{0.13118855996390266, 0.63304451906682857}"
    },
    {
      "_class": "curvePoint",
      "cornerRadius": 0,
      "curveFrom": "{0.31518855996392858, 0.1980445190668263}",
      "curveMode": 3,
      "curveTo": "{0.091188559963939042, 0.30504451906682561}",
      "hasCurveFrom": true,
      "hasCurveTo": true,
      "point": "{0.2271885599639063, 0.24004451906682789}"
    },
    {
      "_class": "curvePoint",
      "cornerRadius": 0,
      "curveFrom": "{0.57618855996389584, 0.12404451906684244}",
      "curveMode": 3,
      "curveTo": "{0.41718855996390403, 0.21704451906683175}",
      "hasCurveFrom": true,
      "hasCurveTo": true,
      "point": "{0.51018855996392176, 0.16304451906682971}"
    },
    {
      "_class": "curvePoint",
      "cornerRadius": 0,
      "curveFrom": "{0.84818855996394404, 0.24204451906683744}",
      "curveMode": 3,
      "curveTo": "{0.62918855996389311, 0.25904451906683335}",
      "hasCurveFrom": true,
      "hasCurveTo": true,
      "point": "{0.73318855996393495, 0.25104451906682357}"
    },
    {
      "_class": "curvePoint",
      "cornerRadius": 0,
      "curveFrom": "{0.84718855996391085, 0.49904451906684244}",
      "curveMode": 4,
      "curveTo": "{0.84118855996393904, 0.34804451906683198}",
      "hasCurveFrom": true,
      "hasCurveTo": true,
      "point": "{0.8451885599639013, 0.43804451906683539}"
    },
    {
      "_class": "curvePoint",
      "cornerRadius": 0,
      "curveFrom": "{0.91418855996391812, 0.61704451906683744}",
      "curveMode": 4,
      "curveTo": "{0.89018855996391721, 0.55804451906683994}",
      "hasCurveFrom": false,
      "hasCurveTo": true,
      "point": "{0.91418855996391812, 0.61704451906683744}"
    }
  ],
  "resizingConstraint": 63,
  "resizingType": 0,
  "rotation": 0,
  "shouldBreakMaskChain": false,
  "style": {
    "_class": "style",
    "do_objectID": "0AC8974B-7F11-490A-B30A-FB3F7935B0A3",
    "endMarkerType": 0,
    "fills": [
      {
        "_class": "fill",
        "color": {
          "_class": "color",
          "alpha": 1,
          "blue": 0.4037829637527466,
          "green": 0.7383424639701843,
          "red": 0.8472057580947876
        },
        "fillType": 0,
        "isEnabled": true,
        "noiseIndex": 0,
        "noiseIntensity": 0,
        "patternFillType": 1,
        "patternTileScale": 1
      }
    ],
    "miterLimit": 10,
    "startMarkerType": 0,
    "windingRule": 1
  }
}