{
  "_class": "shapePath",
  "booleanOperation": -1,
  "clippingMaskMode": 0,
  "do_objectID": "22154749-1153-4CD4-B6EE-4AB8F0CD6C3A",
  "edited": true,
  "exportOptions": {
    "_class": "exportOptions",
    "do_objectID": "483AE543-2DC7-48C0-95C6-3E358958572F",
    "exportFormats": [
    ],
    "includedLayerIds": [
    ],
    "layerOptions": 0,
    "shouldTrim": false
  },
  "frame": {
    "_class": "rect",
    "constrainProportions": false,
    "do_objectID": "8E34F37D-9A08-4D94-BAA0-4A5C6E833C9D",
    "height": 0.5681746893473374,
    "width": 0.5724600309438017,
    "x": 117.8953230573551,
    "y": 55.20713197487776
  },
  "hasClippingMask": false,
  "isClosed": false,
  "isFixedToViewport": false,
  "isFlippedHorizontal": false,
  "isFlippedVertical": false,
  "isLocked": false,
  "isVisible": true,
  "layerListExpandedType": 0,
  "name": "Fill 2321",
  "nameIsFixed": false,
  "pointRadiusBehaviour": 1,
  "points": [
    {
      "_class": "curvePoint",
      "cornerRadius": 0,
      "curveFrom": "{0.62842665926868335, 0.76782860969899502}",
      "curveMode": 4,
      "curveTo": "{0.71342665926869131, 0.6538286096989907}",
      "hasCurveFrom": true,
      "hasCurveTo": false,
      "point": "{0.71342665926869131, 0.6538286096989907}"
    },
    {
      "_class": "curvePoint",
      "cornerRadius": 0,
      "curveFrom": "{0.21542665926870086, 0.62082860969900366}",
      "curveMode": 3,
      "curveTo": "{0.47242665926867744, 0.79682860969899139}",
      "hasCurveFrom": true,
      "hasCurveTo": true,
      "point": "{0.35842665926870154, 0.71882860969898843}"
    },
    {
      "_class": "curvePoint",
      "cornerRadius": 0,
      "curveFrom": "{0.40042665926870313, 0.2198286096989932}",
      "curveMode": 3,
      "curveTo": "{0.19342665926868108, 0.4558286096989832}",
      "hasCurveFrom": true,
      "hasCurveTo": true,
      "point": "{0.30842665926869017, 0.32582860969898775}"
    },
    {
      "_class": "curvePoint",
      "cornerRadius": 0,
      "curveFrom": "{0.77742665926868426, 0.3868286096989948}",
      "curveMode": 2,
      "curveTo": "{0.55542665926870427, 0.20782860969899275}",
      "hasCurveFrom": true,
      "hasCurveTo": true,
      "point": "{0.66642665926869427, 0.29682860969899139}"
    },
    {
      "_class": "curvePoint",
      "cornerRadius": 0,
      "curveFrom": "{0.71342665926869131, 0.6538286096989907}",
      "curveMode": 4,
      "curveTo": "{0.79742665926869449, 0.54082860969899116}",
      "hasCurveFrom": false,
      "hasCurveTo": true,
      "point": "{0.71342665926869131, 0.6538286096989907}"
    }
  ],
  "resizingConstraint": 63,
  "resizingType": 0,
  "rotation": 0,
  "shouldBreakMaskChain": false,
  "style": {
    "_class": "style",
    "do_objectID": "D55BFA34-7EE9-4147-A20A-E4DD49C9EAC1",
    "endMarkerType": 0,
    "fills": [
      {
        "_class": "fill",
        "color": {
          "_class": "color",
          "alpha": 1,
          "blue": 0.4037829637527466,
          "green": 0.7383424639701843,
          "red": 0.8472057580947876
        },
        "fillType": 0,
        "isEnabled": true,
        "noiseIndex": 0,
        "noiseIntensity": 0,
        "patternFillType": 1,
        "patternTileScale": 1
      }
    ],
    "miterLimit": 10,
    "startMarkerType": 0,
    "windingRule": 1
  }
}