{
  "_class": "group",
  "booleanOperation": 0,
  "clippingMaskMode": 0,
  "do_objectID": "56C92F7A-B8D1-4BA3-8C73-81161E687A96",
  "exportOptions": {
    "_class": "exportOptions",
    "do_objectID": "E9170208-74BC-4BDA-9BA9-11047DF347BC",
    "exportFormats": [
    ],
    "includedLayerIds": [
    ],
    "layerOptions": 0,
    "shouldTrim": false
  },
  "frame": {
    "_class": "rect",
    "constrainProportions": false,
    "do_objectID": "A8CEA800-B9A9-4261-BDD2-56B902CF2295",
    "height": 14.4,
    "width": 6.24,
    "x": 249.6,
    "y": 9.120000000000001
  },
  "hasClickThrough": false,
  "hasClippingMask": false,
  "isFixedToViewport": false,
  "isFlippedHorizontal": false,
  "isFlippedVertical": false,
  "isLocked": false,
  "isVisible": true,
  "layerListExpandedType": 2,
  "layers": [
    {
      "class": "shapePath",
      "id": "D60256AD-9127-4872-97A9-92E99369E137"
    }
  ],
  "name": "Next",
  "nameIsFixed": true,
  "resizingConstraint": 63,
  "resizingType": 0,
  "rotation": 180,
  "shouldBreakMaskChain": false,
  "style": {
    "_class": "style",
    "blur": {
      "_class": "blur",
      "center": "{0.5, 0.5}",
      "do_objectID": "CE6B491A-0402-4CEF-A6C1-E029FCB64C3E",
      "isEnabled": false,
      "motionAngle": 0,
      "radius": 4.8,
      "saturation": 1,
      "type": 0
    },
    "do_objectID": "59E51ABD-664A-44A0-B91E-DCD99766B5DF",
    "endMarkerType": 0,
    "miterLimit": 10,
    "startMarkerType": 0,
    "windingRule": 1
  }
}